powerline_watson/__init__.py
powerline_watson/status.py
powerline_watson-1.0.1.dist-info/LICENSE
powerline_watson-1.0.1.dist-info/METADATA
powerline_watson-1.0.1.dist-info/WHEEL
powerline_watson-1.0.1.dist-info/top_level.txt
powerline_watson-1.0.1.dist-info/RECORD
